busysloths_mlox-0.1.0.post266.dist-info/licenses/LICENSE
mlox/__init__.py
mlox/app.py
mlox/cli.py
mlox/config.py
mlox/executors.py
mlox/infra.py
mlox/logging_config.py
mlox/operations.py
mlox/scheduler.py
mlox/secret_manager.py
mlox/server.py
mlox/service.py
mlox/service_registry.py
mlox/session.py
mlox/utils.py
mlox/assets/__init__.py
mlox/assets/cloud-init.yaml
mlox/assets/start-multipass-testbed.sh
mlox/assets/start-multipass.sh
mlox/assets/start-ui.sh
mlox/resources/BMFTR_logo.jpg
mlox/resources/PrototypeFund_logo_dark.png
mlox/resources/PrototypeFund_logo_light.png
mlox/resources/__init__.py
mlox/resources/config.toml
mlox/resources/mlox.png
mlox/resources/mlox_logo.png
mlox/resources/mlox_logo_small.png
mlox/resources/mlox_logo_wide.png
mlox/servers/__init__.py
mlox/servers/local/local.py
mlox/servers/local/mlox-server.local.yaml
mlox/servers/ubuntu/__init__.py
mlox/servers/ubuntu/docker.py
mlox/servers/ubuntu/k3s.py
mlox/servers/ubuntu/mlox-server.ubuntu.docker.yaml
mlox/servers/ubuntu/mlox-server.ubuntu.k3s.yaml
mlox/servers/ubuntu/mlox-server.ubuntu.native.yaml
mlox/servers/ubuntu/mlox-server.ubuntu.simple.yaml
mlox/servers/ubuntu/native.py
mlox/servers/ubuntu/simple.py
mlox/servers/ubuntu/ui_docker.py
mlox/servers/ubuntu/ui_k3s.py
mlox/servers/ubuntu/ui_native.py
mlox/servers/ubuntu/ui_simple.py
mlox/services/__init__.py
mlox/services/utils_ui.py
mlox/services/airflow/__init__.py
mlox/services/airflow/docker-compose-airflow-2.9.2.yaml
mlox/services/airflow/docker-compose-airflow-3.0.1.yaml
mlox/services/airflow/docker.py
mlox/services/airflow/mlox.2.9.2.yaml
mlox/services/airflow/mlox.3.0.1.yaml
mlox/services/airflow/ui.py
mlox/services/feast/Dockerfile
mlox/services/feast/__init__.py
mlox/services/feast/client.py
mlox/services/feast/docker-compose-feast.yaml
mlox/services/feast/docker.py
mlox/services/feast/mlox.feast.yaml
mlox/services/feast/ui.py
mlox/services/gcp/__init__.py
mlox/services/gcp/bigquery.py
mlox/services/gcp/bq_service.py
mlox/services/gcp/bq_ui.py
mlox/services/gcp/cloud_storage.py
busysloths_mlox-0.1.0.post266.dist-info/METADATA
busysloths_mlox-0.1.0.post266.dist-info/WHEEL
busysloths_mlox-0.1.0.post266.dist-info/entry_points.txt
busysloths_mlox-0.1.0.post266.dist-info/top_level.txt
busysloths_mlox-0.1.0.post266.dist-info/RECORD
