Metadata-Version: 2.4
Name: busysloths-mlox
Version: 0.1.0.post266
Summary: Accelerate your ML journey—deploy production-ready MLOps in minutes, not months.
Author-email: nicococo <contact@mlox.org>
License: MIT License
Project-URL: Homepage, https://busysloths.github.io/mlox/mlox.html
Project-URL: Tracker, https://github.com/busysloths/mlox/issues
Project-URL: Source, https://github.com/busysloths/mlox
Project-URL: Examples, https://github.com/busysloths/mlox
Keywords: Infrastructure,Server,Service,Dashboard,Opinionated,MLOps
Classifier: Development Status :: 3 - Alpha
Classifier: Intended Audience :: Developers
Classifier: Topic :: Software Development
Classifier: Topic :: System :: Distributed Computing
Classifier: Topic :: Internet
Classifier: Topic :: Database
Classifier: Programming Language :: Python :: 3
Classifier: License :: OSI Approved :: MIT License
Classifier: Operating System :: OS Independent
Requires-Python: >=3.11
License-File: LICENSE
Requires-Dist: dacite==1.9.2
Requires-Dist: pyyaml==6.0.2
Requires-Dist: fabric==3.2.2
Requires-Dist: paramiko==3.4.1
Requires-Dist: cryptography==43.0.1
Requires-Dist: passlib==1.7.4
Requires-Dist: typer==0.17.4
Requires-Dist: grpcio==1.73.1
Requires-Dist: kafka-python-ng==2.2.3
Requires-Dist: bcrypt>=5.0.0
Provides-Extra: gcp
Requires-Dist: pandas>=2.2; extra == "gcp"
Requires-Dist: gspread==6.2.1; extra == "gcp"
Requires-Dist: pandas-gbq==0.29.2; extra == "gcp"
Requires-Dist: google-cloud-storage>=2.10; extra == "gcp"
Requires-Dist: google-cloud-bigquery>=3.10; extra == "gcp"
Requires-Dist: google-cloud-secret-manager>=2.18; extra == "gcp"
Provides-Extra: feast
Requires-Dist: feast==0.54.0; extra == "feast"
Requires-Dist: feast[postgres]==0.54.0; extra == "feast"
Provides-Extra: minio
Requires-Dist: boto3==1.40.56; extra == "minio"
Provides-Extra: dev
Requires-Dist: colorama==0.4.6; extra == "dev"
Requires-Dist: feast==0.54.0; extra == "dev"
Requires-Dist: feast[postgres]==0.54.0; extra == "dev"
Requires-Dist: boto3==1.40.56; extra == "dev"
Requires-Dist: streamlit==1.50.0; extra == "dev"
Requires-Dist: streamlit-vis-timeline==0.3.0; extra == "dev"
Requires-Dist: textual==6.3.0; extra == "dev"
Requires-Dist: textual-dev==1.8.0; extra == "dev"
Requires-Dist: backports.tarfile>=1.0; extra == "dev"
Requires-Dist: pandas>=2.2; extra == "dev"
Requires-Dist: numpy>=1.26; extra == "dev"
Requires-Dist: gspread==6.2.1; extra == "dev"
Requires-Dist: pandas-gbq==0.29.2; extra == "dev"
Requires-Dist: google-cloud-storage>=2.10; extra == "dev"
Requires-Dist: google-cloud-bigquery>=3.10; extra == "dev"
Requires-Dist: google-cloud-secret-manager>=2.18; extra == "dev"
Requires-Dist: mlflow==2.22.2; extra == "dev"
Requires-Dist: mlserver==1.7.1; extra == "dev"
Requires-Dist: psutil==7.1.2; extra == "dev"
Requires-Dist: opentelemetry-api==1.33.1; extra == "dev"
Requires-Dist: opentelemetry-sdk==1.33.1; extra == "dev"
Requires-Dist: opentelemetry-exporter-otlp==1.33.1; extra == "dev"
Requires-Dist: redis>=4.6; extra == "dev"
Requires-Dist: influxdb>=5.3; extra == "dev"
Requires-Dist: pytest>=8.3; extra == "dev"
Requires-Dist: pytest-cov>=4.1; extra == "dev"
Requires-Dist: pytest-mock>=3.11; extra == "dev"
Requires-Dist: pytest-sugar>=1.1.1; extra == "dev"
Requires-Dist: flake8>=6.1; extra == "dev"
Requires-Dist: pdoc>=12.0; extra == "dev"
Requires-Dist: build>=1.1; extra == "dev"
Requires-Dist: twine>=4.0; extra == "dev"
Requires-Dist: psycopg2-binary>=2.9; extra == "dev"
Requires-Dist: colorama>=0.4.6; extra == "dev"
Requires-Dist: go-task-bin>=3.44.1; extra == "dev"
Requires-Dist: debugpy==1.8.16; extra == "dev"
Dynamic: license-file
